foapy/__init__.py
foapy/characteristics/__init__.py
foapy/characteristics/_arithmetic_mean.py
foapy/characteristics/_average_remoteness.py
foapy/characteristics/_depth.py
foapy/characteristics/_descriptive_information.py
foapy/characteristics/_geometric_mean.py
foapy/characteristics/_identifying_information.py
foapy/characteristics/_regularity.py
foapy/characteristics/_uniformity.py
foapy/characteristics/_volume.py
foapy/characteristics/ma/__init__.py
foapy/characteristics/ma/_arithmetic_mean.py
foapy/characteristics/ma/_average_remoteness.py
foapy/characteristics/ma/_depth.py
foapy/characteristics/ma/_geometric_mean.py
foapy/characteristics/ma/_identifying_information.py
foapy/characteristics/ma/_periodicity.py
foapy/characteristics/ma/_uniformity.py
foapy/characteristics/ma/_volume.py
foapy/core/__init__.py
foapy/core/_alphabet.py
foapy/core/_binding.py
foapy/core/_intervals.py
foapy/core/_mode.py
foapy/core/_order.py
foapy/exceptions/__init__.py
foapy/exceptions/inconsistent_order.py
foapy/exceptions/not_1d_array.py
foapy/ma/__init__.py
foapy/ma/_alphabet.py
foapy/ma/_intervals.py
foapy/ma/_order.py
foapy-0.0.21.dist-info/licenses/LICENSE.txt
foapy-0.0.21.dist-info/METADATA
foapy-0.0.21.dist-info/WHEEL
foapy-0.0.21.dist-info/top_level.txt
foapy-0.0.21.dist-info/RECORD
