Metadata-Version: 2.4
Name: foapy
Version: 0.0.21
Summary: Formal order analysis library
Home-page: https://github.com/intervals-mining-lab/foapy
Author: FOARLab
Author-email: development@foarlab.org
License: BSD-3-Clause
Project-URL: Documentation, https://pyscaffold.org/
Platform: any
Classifier: Development Status :: 4 - Beta
Classifier: Programming Language :: Python
License-File: LICENSE.txt
Requires-Dist: importlib-metadata; python_version < "3.8"
Requires-Dist: numpy>=1.20
Provides-Extra: testing
Requires-Dist: setuptools; extra == "testing"
Requires-Dist: pytest; extra == "testing"
Requires-Dist: pytest-cov; extra == "testing"
Requires-Dist: asv; extra == "testing"
Dynamic: license-file
